task_ai/__init__.py
task_ai/cli.py
task_ai/main.py
task_ai/anonymizer/__init__.py
task_ai/anonymizer/abort_actions_anonymizer.py
task_ai/anonymizer/base_anonymizer.py
task_ai/anonymizer/email_notifications_anonymizer.py
task_ai/anonymizer/environment_anonymizer.py
task_ai/anonymizer/exclusive_tasks_anonymizer.py
task_ai/anonymizer/notes_anonymizer.py
task_ai/anonymizer/set_variable_actions_anonymizer.py
task_ai/anonymizer/snmp_notifications_anonymizer.py
task_ai/anonymizer/system_operations_anonymizer.py
task_ai/anonymizer/variables_anonymizer.py
task_ai/anonymizer/virtual_resources_anonymizer.py
task_ai/config/__init__.py
task_ai/models/__init__.py
task_ai/models/task.py
task_ai/parsers/__init__.py
task_ai/parsers/abort_actions_parser.py
task_ai/parsers/base_parser.py
task_ai/parsers/email_notifications_parser.py
task_ai/parsers/environment_parser.py
task_ai/parsers/exclusive_tasks_parser.py
task_ai/parsers/notes_parser.py
task_ai/parsers/set_variable_actions_parser.py
task_ai/parsers/snmp_notifications_parser.py
task_ai/parsers/system_operations_parser.py
task_ai/parsers/variables_parser.py
task_ai/parsers/virtual_resources_parser.py
task_ai/processors/__init__.py
task_ai/processors/anonymizer_processor.py
task_ai/processors/description_processor.py
task_ai/processors/parsing_processor.py
task_ai/prompts/examples/taskUnix.yaml
task_ai/utils/__init__.py
task_ai/utils/config_reader.py
task_ai-0.0.3.dist-info/METADATA
task_ai-0.0.3.dist-info/WHEEL
task_ai-0.0.3.dist-info/entry_points.txt
task_ai-0.0.3.dist-info/top_level.txt
task_ai-0.0.3.dist-info/RECORD
