Metadata-Version: 2.1
Name: task-ai
Version: 0.0.3
Summary: A CLI tool for describing tasks using LLM tools
Author: Huseyin G.
Author-email: huseyim@gmail.com
License: CC BY-NC 4.0
Classifier: Programming Language :: Python :: 3
Classifier: License :: OSI Approved :: MIT License
Classifier: Operating System :: OS Independent
Requires-Python: >=3.7
Requires-Dist: setuptools (>=44.1.1)
Requires-Dist: click (==8.1.6)
Requires-Dist: PyYAML
Requires-Dist: requests
